aws_rag_bot/__init__.py
aws_rag_bot/aws_opensearch_vector_database.py
aws_rag_bot/kustomer.py
aws_rag_bot/prompt_library.py
aws_rag_bot/rag_chatbot.py
aws_rag_bot-0.1.16.dist-info/LICENSE
aws_rag_bot-0.1.16.dist-info/METADATA
aws_rag_bot-0.1.16.dist-info/WHEEL
aws_rag_bot-0.1.16.dist-info/RECORD
