Metadata-Version: 2.1
Name: aws-rag-bot
Version: 0.1.16
Summary: 
Home-page: https://github.com/harvest2o-llc/aws-rag-bot
License: MIT
Keywords: aws,rag,bedrock,opensearch,vector database
Author: danjamk
Author-email: dan@risegardens.com
Requires-Python: >=3.11,<3.12
Classifier: License :: OSI Approved :: MIT License
Classifier: Programming Language :: Python :: 3
Classifier: Programming Language :: Python :: 3.11
Requires-Dist: anthropic (>=0.16.0,<0.17.0)
Requires-Dist: boto3 (>=1.34.51,<2.0.0)
Requires-Dist: cohere (>=4.51,<5.0)
Requires-Dist: docx2txt (>=0.8,<0.9)
Requires-Dist: langchain (>=0.1.11,<0.2.0)
Requires-Dist: langchain-google-genai (>=0.0.9,<0.0.10)
Requires-Dist: langchain-openai (>=0.0.8,<0.0.9)
Requires-Dist: opensearch-py (>=2.4.2,<3.0.0)
Requires-Dist: pyarrow (>=15.0.2,<16.0.0)
Requires-Dist: python-dotenv (>=1.0.1,<2.0.0)
Requires-Dist: ragas (>=0.1.3,<0.2.0)
Requires-Dist: requests (>=2.31.0,<3.0.0)
Requires-Dist: requests-aws4auth (>=1.2.3,<2.0.0)
Requires-Dist: selenium (>=4.18.1,<5.0.0)
Requires-Dist: sentence-transformers (>=2.5.0,<3.0.0)
Requires-Dist: torch (>=2.2.1,<3.0.0)
Requires-Dist: transformers (>=4.38.1,<5.0.0)
Requires-Dist: unstructured (>=0.12.5,<0.13.0)
Project-URL: Repository, https://github.com/harvest2o-llc/aws-rag-bot
